{"schema":{"namespace":"EF.Contexts","alias":"Self","annotation:UseStrongSpatialTypes":"false","xmlns:annotation":"http://schemas.microsoft.com/ado/2009/02/edm/annotation","xmlns:customannotation":"http://schemas.microsoft.com/ado/2013/11/edm/customannotation","xmlns":"http://schemas.microsoft.com/ado/2009/11/edm","cSpaceOSpaceMapping":"[[\"EF.Contexts.ValueItem\",\"EF.Models.ValueItem\"]]","entityType":{"name":"ValueItem","customannotation:ClrType":"EF.Models.ValueItem, EF, Version=1.0.0.0, Culture=neutral, PublicKeyToken=null","key":{"propertyRef":{"name":"Key"}},"property":[{"name":"Key","type":"Edm.Int64","nullable":"false","annotation:StoreGeneratedPattern":"Identity"},{"name":"Value","type":"Edm.String","maxLength":"Max","fixedLength":"false","unicode":"true"}]},"entityContainer":{"name":"ValueContext","customannotation:UseClrTypes":"true","entitySet":{"name":"ValueItems","entityType":"Self.ValueItem"}}}}